{"frames": [

{
	"filename": "lg_slime_punch_R_0011.png",
	"frame": {"x":488,"y":0,"w":505,"h":394},
	"rotated": false,
	"trimmed": false,
	"spriteSourceSize": {"x":0,"y":0,"w":505,"h":394},
	"sourceSize": {"w":505,"h":394}
},
{
	"filename": "lg_slime_punch_R_0012.png",
	"frame": {"x":0,"y":0,"w":488,"h":394},
	"rotated": false,
	"trimmed": false,
	"spriteSourceSize": {"x":0,"y":0,"w":488,"h":394},
	"sourceSize": {"w":488,"h":394}
},
{
	"filename": "lg_slime_punch_R_0013.png",
	"frame": {"x":734,"y":396,"w":761,"h":391},
	"rotated": false,
	"trimmed": false,
	"spriteSourceSize": {"x":0,"y":0,"w":761,"h":391},
	"sourceSize": {"w":761,"h":391}
},
{
	"filename": "lg_slime_punch_R_0014.png",
	"frame": {"x":993,"y":0,"w":690,"h":396},
	"rotated": false,
	"trimmed": false,
	"spriteSourceSize": {"x":0,"y":0,"w":690,"h":396},
	"sourceSize": {"w":690,"h":396}
},
{
	"filename": "lg_slime_punch_R_0015.png",
	"frame": {"x":0,"y":817,"w":781,"h":422},
	"rotated": false,
	"trimmed": false,
	"spriteSourceSize": {"x":0,"y":0,"w":781,"h":422},
	"sourceSize": {"w":781,"h":422}
},
{
	"filename": "lg_slime_punch_R_0016.png",
	"frame": {"x":781,"y":817,"w":802,"h":423},
	"rotated": false,
	"trimmed": false,
	"spriteSourceSize": {"x":0,"y":0,"w":802,"h":423},
	"sourceSize": {"w":802,"h":423}
},
{
	"filename": "lg_slime_punch_R_0017.png",
	"frame": {"x":0,"y":1240,"w":814,"h":427},
	"rotated": false,
	"trimmed": false,
	"spriteSourceSize": {"x":0,"y":0,"w":814,"h":427},
	"sourceSize": {"w":814,"h":427}
},
{
	"filename": "lg_slime_punch_R_0018.png",
	"frame": {"x":814,"y":1240,"w":823,"h":427},
	"rotated": false,
	"trimmed": false,
	"spriteSourceSize": {"x":0,"y":0,"w":823,"h":427},
	"sourceSize": {"w":823,"h":427}
},
{
	"filename": "lg_slime_punch_R_0019.png",
	"frame": {"x":0,"y":396,"w":734,"h":421},
	"rotated": false,
	"trimmed": false,
	"spriteSourceSize": {"x":0,"y":0,"w":734,"h":421},
	"sourceSize": {"w":734,"h":421}
}],
"meta": {
	"app": "https://www.codeandweb.com/texturepacker",
	"version": "1.0",
	"image": "lg_slime_punch_2_R.png",
	"format": "RGBA8888",
	"size": {"w":1683,"h":1667},
	"scale": "1",
	"smartupdate": "$TexturePacker:SmartUpdate:3cce935e84bb37376d941def62869a4b:9d9557c68f83f0f32d951285045364b4:58c53f811c61afe4c7bfe1f71c745667$"
}
}
